bilibili_storytree/__init__.py
bilibili_storytree/convertor.py
bilibili_storytree/decode.js
bilibili_storytree/gen_code.py
bilibili_storytree/graph_nodes.py
bilibili_storytree/graph_script.py
bilibili_storytree/story_graph.py
bilibili_storytree-0.1.1.dist-info/WHEEL
bilibili_storytree-0.1.1.dist-info/METADATA
bilibili_storytree-0.1.1.dist-info/RECORD
