Metadata-Version: 2.1
Name: bilibili-storytree
Version: 0.1.1
Summary: API to create story graph for interactivate video in bilibili
Home-page: https://github.com/phigrey/bilibili-storytree.git
Author: Phoenix Grey
Author-email: phoenix.grey0108@gmail.com
Requires-Python: >=3.8,<4.0
Classifier: Programming Language :: Python :: 3
Classifier: Programming Language :: Python :: 3.8
Classifier: Programming Language :: Python :: 3.9
Requires-Dist: PyExecJS (>=1.5.1,<2.0.0)
Project-URL: Repository, https://github.com/phigrey/bilibili-storytree.git
